Workbook

Sheet Inputs
A1: Item | B1: Mar 2021 | C1: Mar 2022 | D1: Mar 2023 | E1: Mar 2024 | F1: Mar 2025
A2: Revenue Growth % | B2: 0 | C2: 0 | D2: 0 | E2: 0 | F2: 0.08 | G2: 0.08 | H2: 0.08 | I2: 0.08 | J2: 0.08
A3: EBITDA Margin % | B3: 0 | C3: 0 | D3: 0 | E3: 0 | F3: 0.14 | G3: 0.14 | H3: 0.14 | I3: 0.14 | J3: 0.14
A4: Effective Tax Rate % | B4: 0 | C4: 0 | D4: 0 | E4: 0 | F4: 0.25 | G4: 0.25 | H4: 0.25 | I4: 0.25 | J4: 0.25
A5: Capex as % of Sales | B5: 0 | C5: 0 | D5: 0 | E5: 0 | F5: 0.05 | G5: 0.05 | H5: 0.05 | I5: 0.05 | J5: 0.05
A6: Working Capital Days | B6: 0 | C6: 0 | D6: 0 | E6: 0 | F6: 45 | G6: 45 | H6: 45 | I6: 45 | J6: 45
A9: WACC Assumptions
A10: Risk Free Rate | B10: 0.067
A11: Beta | B11: 1.2
A12: Market Premium | B12: 0.05
A13: Cost of Debt (Pre-tax) | B13: 0.075
A14: Tax Rate | B14: 0.25
A15: Target Debt/Equity | B15: 0.5

Sheet IS
A1: Item | B1: Mar 2021 | C1: Mar 2022 | D1: Mar 2023 | E1: Mar 2024 | F1: Mar 2025
A2: Sales + | B2: 132008 | C2: 195059 | D2: 223202 | E2: 215962 | F2: 238496
A3: Expenses + | B3: 114449 | C3: 166712 | D3: 200536 | E3: 192090 | F3: 206691
A4: Operating Profit | B4: 17559 | C4: 28347 | D4: 22666 | E4: 23872 | F4: 31805
A5: OPM % | B5: 0 | C5: 0 | D5: 0 | E5: 0 | F5: 0
A6: Other Income + | B6: -987 | C6: 1253 | D6: 1307 | E6: 1519 | F6: 1832
A7: Interest | B7: 3738 | C7: 3768 | D7: 3646 | E7: 3858 | F7: 3419
A8: Depreciation | B8: 6628 | C8: 6729 | D8: 7086 | E8: 7521 | F8: 7881
A9: Profit before tax | B9: 6206 | C9: 19103 | D9: 13241 | E9: 14012 | F9: 22337
A10: Tax % | B10: 0 | C10: 0 | D10: 0 | E10: 0 | F10: 0
A11: Net Profit + | B11: 3483 | C11: 13730 | D11: 10097 | E11: 10155 | F11: 16002
A12: EPS in Rs | B12: 15.5 | C12: 61.1 | D12: 44.93 | E12: 45.19 | F12: 71.2
A13: Dividend Payout % | B13: 0 | C13: 0 | D13: 0 | E13: 0 | F13: 0

Sheet BS
A1: Item | B1: Mar 2021 | C1: Mar 2022 | D1: Mar 2023 | E1: Mar 2024 | F1: Mar 2025
A2: Equity Capital | B2: 222 | C2: 222 | D2: 222 | E2: 222 | F2: 222
A3: Reserves | B3: 66311 | C3: 77969 | D3: 94584 | E3: 105924 | F3: 123487
A4: Borrowings + | B4: 67206 | C4: 64486 | D4: 60291 | E4: 56356 | F4: 63929
A5: Other Liabilities + | B5: 55083 | C5: 79178 | D5: 68392 | E5: 68221 | F5: 76662
A6: Total Liabilities | B6: 188822 | C6: 221855 | D6: 223489 | E6: 230723 | F6: 264300
A7: Fixed Assets + | B7: 100269 | C7: 106874 | D7: 110626 | E7: 111810 | F7: 116556
A8: CWIP | B8: 10202 | C8: 4945 | D8: 7700 | E8: 14867 | F8: 27397
A9: Investments | B9: 17133 | C9: 14119 | D9: 14116 | E9: 15444 | F9: 24158
A10: Other Assets + | B10: 61218 | C10: 95917 | D10: 91047 | E10: 88602 | F10: 96189
A11: Total Assets | B11: 188822 | C11: 221855 | D11: 223489 | E11: 230723 | F11: 264300

Sheet CF
A1: Item | B1: Mar 2021 | C1: Mar 2022 | D1: Mar 2023 | E1: Mar 2024 | F1: Mar 2025
A2: Cash from Operating Activity + | B2: 17232 | C2: 16838 | D2: 19208 | E2: 24056 | F2: 24410
A3: Cash from Investing Activity + | B3: -25280 | C3: -6773 | D3: -7559 | E3: -14267 | F3: -24609
A4: Cash from Financing Activity + | B4: -4882 | C4: -6765 | D4: -10450 | E4: -10817 | F4: -1816
A5: Net Cash Flow | B5: -12930 | C5: 3300 | D5: 1199 | E5: -1028 | F5: -2015

Sheet DCF
A1: DCF Model | B1: FY26E | C1: FY27E | D1: FY28E | E1: FY29E | F1: FY30E
A2: Revenue | B2: =IS!F3*(1+Inputs!F2) -> 0 | C2: =B2*(1+Inputs!G2) -> 0 | D2: =C2*(1+Inputs!H2) -> 0 | E2: =D2*(1+Inputs!I2) -> 0 | F2: =E2*(1+Inputs!J2) -> 0
A3: EBITDA | B3: =B2*Inputs!B3 -> 0 | C3: =C2*Inputs!C3 -> 0 | D3: =D2*Inputs!D3 -> 0 | E3: =E2*Inputs!E3 -> 0 | F3: =F2*Inputs!F3 -> 0
A4: D&A | B4: =B2*0.03 -> 0 | C4: =C2*0.03 -> 0 | D4: =D2*0.03 -> 0 | E4: =E2*0.03 -> 0 | F4: =F2*0.03 -> 0
A5: EBIT | B5: =B3-B4 -> 0 | C5: =C3-C4 -> 0 | D5: =D3-D4 -> 0 | E5: =E3-E4 -> 0 | F5: =F3-F4 -> 0
A6: Tax | B6: =B5*Inputs!B14 -> 0 | C6: =C5*Inputs!B14 -> 0 | D6: =D5*Inputs!B14 -> 0 | E6: =E5*Inputs!B14 -> 0 | F6: =F5*Inputs!B14 -> 0
A7: NOPAT | B7: =B5-B6 -> 0 | C7: =C5-C6 -> 0 | D7: =D5-D6 -> 0 | E7: =E5-E6 -> 0 | F7: =F5-F6 -> 0
A8: Capex | B8: =B2*Inputs!B5 -> 0 | C8: =C2*Inputs!C5 -> 0 | D8: =D2*Inputs!D5 -> 0 | E8: =E2*Inputs!E5 -> 0 | F8: =F2*Inputs!F5 -> 0
A9: Change in WC | B9: =B2*0.02 -> 0 | C9: =C2*0.02 -> 0 | D9: =D2*0.02 -> 0 | E9: =E2*0.02 -> 0 | F9: =F2*0.02 -> 0
A10: FCFF | B10: =B7+B4-B8-B9 -> 0 | C10: =C7+C4-C8-C9 -> 0 | D10: =D7+D4-D8-D9 -> 0 | E10: =E7+E4-E8-E9 -> 0 | F10: =F7+F4-F8-F9 -> 0
A12: WACC Calculation
A13: Cost of Equity (Ke) | B13: =Inputs!B10 + Inputs!B11*Inputs!B12 -> 0
A14: Cost of Debt (Kd, After-tax) | B14: =Inputs!B13*(1-Inputs!B14) -> 0
A15: WACC | B15: =B13*0.6 + B14*0.4 -> 0
A17: Discount Factor | B17: =1/(1+$B$15)^1 -> 0 | C17: =1/(1+$B$15)^2 -> 0 | D17: =1/(1+$B$15)^3 -> 0 | E17: =1/(1+$B$15)^4 -> 0 | F17: =1/(1+$B$15)^5 -> 0
A18: Present Value of FCFF | B18: =B10*B17 -> 0 | C18: =C10*C17 -> 0 | D18: =D10*D17 -> 0 | E18: =E10*E17 -> 0 | F18: =F10*F17 -> 0
A20: Terminal Value Assumptions
A21: Terminal Growth Rate | B21: 0.03
A22: Implied TV (Gordon Growth) | B22: =F10*(1+B21)/(B15-B21) -> 0
A23: PV of Terminal Value | B23: =B22*F17 -> 0
A25: Enterprise Value | B25: =SUM(B18:F18)+B23 -> 0
A26: Less: Net Debt | B26: 40000
A27: Equity Value | B27: =B25-B26 -> 0
A28: Shares Outstanding (Cr) | B28: 222
A29: Implied Share Price | B29: =B27/B28 -> 0

Sheet Comps
A1: Company | B1: Ticker | C1: Price (INR) | D1: Market Cap (Cr) | E1: EV (Cr) | F1: Revenue (Cr) | G1: EBITDA (Cr) | H1: P/E | I1: EV/EBITDA | J1: P/B
A2: Hindalco | B2: HINDALCO | C2: 964 | D2: 217138 | E2: 280000 | F2: 238496 | G2: 26000 | H2: 12.1 | I2: 8 | J2: 2.2
A3: Vedanta | B3: VEDL | C3: 595 | D3: 269836 | E3: 320000 | F3: 150000 | G3: 35000 | H3: 18.6 | I3: 7.8 | J3: 2.5
A4: Tata Steel | B4: TATASTEEL | C4: 185 | D4: 259907 | E4: 340000 | F4: 230000 | G4: 24000 | H4: 28.3 | I4: 6.8 | J4: 2.8
A5: NALCO | B5: NATIONALUM | C5: 365 | D5: 67551 | E5: 65000 | F5: 14000 | G5: 3500 | H5: 12.9 | I5: 7.2 | J5: 2.1
A6: JSW Steel | B6: JSWSTEEL | C6: 1250 | D6: 306024 | E6: 380000 | F6: 175000 | G6: 29000 | H6: 40.7 | I6: 14.2 | J6: 3.5
A7: SAIL | B7: SAIL | C7: 161 | D7: 66831 | E7: 100000 | F7: 105000 | G7: 10000 | H7: 24 | I7: 9.1 | J7: 1.2

Sheet Scenarios
A1: Scenario Analysis
A2: Metric | B2: Bear | C2: Base | D2: Bull
A3: Revenue Growth | B3: 0.04 | C3: 0.08 | D3: 0.12
A4: EBITDA Margin | B4: 0.1 | C4: 0.14 | D4: 0.18
A5: WACC | B5: 0.12 | C5: 0.1 | D5: 0.09
A7: Instructions: Copy these values to Inputs sheet to test scenarios.
